AUTHORS
CHANGES
LICENSE
MANIFEST.in
Makefile
TODO
ez_setup.py
setup.cfg
setup.py
Jinja.egg-info/PKG-INFO
Jinja.egg-info/SOURCES.txt
Jinja.egg-info/dependency_links.txt
Jinja.egg-info/entry_points.txt
Jinja.egg-info/native_libs.txt
Jinja.egg-info/not-zip-safe
Jinja.egg-info/requires.txt
Jinja.egg-info/top_level.txt
docs/html/altsyntax.html
docs/html/api.html
docs/html/builtins.html
docs/html/changelog.html
docs/html/debugging.html
docs/html/designerdoc.html
docs/html/devintro.html
docs/html/devrecipies.html
docs/html/escaping.html
docs/html/filters.html
docs/html/frameworks.html
docs/html/fromdjango.html
docs/html/i18n.html
docs/html/index.html
docs/html/inheritance.html
docs/html/installation.html
docs/html/jinjabanner.png
docs/html/jinjalogo.png
docs/html/loaders.html
docs/html/objects.html
docs/html/recipies.html
docs/html/scopes.html
docs/html/streaming.html
docs/html/style.css
docs/html/templatei18n.html
docs/html/tests.html
docs/html/translators.html
docs/html/watermark.png
docs/src/altsyntax.txt
docs/src/api.txt
docs/src/builtins.txt
docs/src/changelog.txt
docs/src/debugging.txt
docs/src/designerdoc.txt
docs/src/devintro.txt
docs/src/devrecipies.txt
docs/src/escaping.txt
docs/src/filters.txt
docs/src/frameworks.txt
docs/src/fromdjango.txt
docs/src/i18n.txt
docs/src/index.txt
docs/src/inheritance.txt
docs/src/installation.txt
docs/src/loaders.txt
docs/src/objects.txt
docs/src/recipies.txt
docs/src/scopes.txt
docs/src/streaming.txt
docs/src/templatei18n.txt
docs/src/tests.txt
docs/src/translators.txt
jinja/__init__.py
jinja/_debugger.c
jinja/_native.py
jinja/_speedups.c
jinja/constants.py
jinja/datastructure.py
jinja/debugger.py
jinja/defaults.py
jinja/environment.py
jinja/exceptions.py
jinja/filters.py
jinja/lexer.py
jinja/loaders.py
jinja/nodes.py
jinja/parser.py
jinja/plugin.py
jinja/tests.py
jinja/utils.py
jinja/translators/__init__.py
jinja/translators/python.py
tests/conftest.py
tests/test_filters.py
tests/test_filters.pyc
tests/test_forloop.py
tests/test_forloop.pyc
tests/test_i18n.py
tests/test_i18n.pyc
tests/test_ifcondition.py
tests/test_ifcondition.pyc
tests/test_inheritance.py
