Metadata-Version: 1.0
Name: Jinja
Version: 1.2
Summary: A small but fast and easy to use stand-alone template engine written in pure python.
Home-page: http://jinja.pocoo.org/
Author: Armin Ronacher
Author-email: armin.ronacher@active-4.com
License: BSD
Keywords: python.templating.engines
Platform: UNKNOWN
Classifier: Development Status :: 5 - Production/Stable
Classifier: Environment :: Web Environment
Classifier: Intended Audience :: Developers
Classifier: License :: OSI Approved :: BSD License
Classifier: Operating System :: OS Independent
Classifier: Programming Language :: Python
Classifier: Topic :: Internet :: WWW/HTTP :: Dynamic Content
Classifier: Topic :: Software Development :: Libraries :: Python Modules
Classifier: Topic :: Text Processing :: Markup :: HTML
